py621dl/__init__.py
py621dl/__main__.py
py621dl/config.toml
py621dl/downloader.py
py621dl/exceptions.py
py621dl/net.py
py621dl/reader.py
py621dl-0.1a1.dev0.dist-info/LICENSE
py621dl-0.1a1.dev0.dist-info/WHEEL
py621dl-0.1a1.dev0.dist-info/METADATA
py621dl-0.1a1.dev0.dist-info/RECORD
