Metadata-Version: 2.1
Name: py621dl
Version: 0.1a1.dev0
Summary: A downloader for e621.net with meant for iterability, using e621 db post exports, designed for deep learning.
Home-page: https://pypi.org/project/py621dl
License: GPL-3.0-or-later
Author: slobodaapl
Author-email: slobodaapl@gmail.com
Requires-Python: >=3.11
Classifier: Development Status :: 1 - Planning
Classifier: Intended Audience :: Developers
Classifier: License :: OSI Approved :: GNU General Public License v3 (GPLv3)
Classifier: License :: OSI Approved :: GNU General Public License v3 or later (GPLv3+)
Classifier: Natural Language :: English
Classifier: Programming Language :: Python :: 3
Classifier: Programming Language :: Python :: 3.11
Classifier: Programming Language :: Python :: 3.11
Requires-Dist: Pillow
Requires-Dist: numpy
Requires-Dist: opencv-python
Requires-Dist: pandas
Requires-Dist: requests
Project-URL: Repository, https://github.com/slobodaapl/py621dl
